pygifconvt_JUH7942/__init__.py
pygifconvt_JUH7942/converter.py
pygifconvt_JUH7942-1.0.0.dist-info/LICENSE
pygifconvt_JUH7942-1.0.0.dist-info/METADATA
pygifconvt_JUH7942-1.0.0.dist-info/WHEEL
pygifconvt_JUH7942-1.0.0.dist-info/top_level.txt
pygifconvt_JUH7942-1.0.0.dist-info/RECORD
