Metadata-Version: 2.1
Name: pygifconvt-JUH7942
Version: 1.0.0
Summary: Test package for distribution
Home-page: UNKNOWN
Author: JeongUiHyeon
Author-email: wibd0669@gmail.com
License: UNKNOWN
Keywords: GIFCONVERTER,gifconverter
Platform: UNKNOWN
Classifier: Programming Language :: Python :: 3
Classifier: License :: OSI Approved :: MIT License
Classifier: Operating System :: OS Independent
Requires-Python: >=3
License-File: LICENSE
Requires-Dist: pillow
